stark_place/commands/__init__.py
stark_place/commands/general_manager.py
stark_place/examples/context.py
stark_place/examples/custom_run.py
stark_place/examples/hello_world.py
stark_place/examples/keyboard_trigger.py
stark_place/examples/porcupine_wakeword_trigger.py
stark_place/notifications/sound.py
stark_place/triggers/keyboard_key.py
stark_place/triggers/porcupine.py
stark_place-1.1.0.dist-info/LICENSE.md
stark_place-1.1.0.dist-info/METADATA
stark_place-1.1.0.dist-info/WHEEL
stark_place-1.1.0.dist-info/RECORD
